LICENSE
async_email/__init__.py
async_email/apps.py
async_email/conf.py
async_email/email/__init__.py
async_email/email/exceptions.py
async_email/email/template.py
async_email/email/utils.py
async_email/exceptions.py
async_email/models.py
async_email/task.py
async_email/tasks.py
async_email-0.1.0.dist-info/LICENSE
async_email-0.1.0.dist-info/WHEEL
async_email-0.1.0.dist-info/METADATA
async_email-0.1.0.dist-info/RECORD
